{"item":[{"name":"admin","description":"","item":[{"name":"subscription","description":"","item":[{"id":"838c23d0-29a6-43a3-b7b5-ad6e1d310aa7","name":"List subscriptions","request":{"name":"List subscriptions","description":{"content":"list subscriptions","type":"text/plain"},"url":{"path":["admin","subscription"],"host":["{{baseUrl}}"],"query":[],"variable":[]},"header":[{"key":"Accept","value":"application/json"}],"method":"GET","body":{},"auth":null},"response":[{"id":"5fd31376-74c5-4f54-ae6d-96f99e748632","name":"OK","originalRequest":{"url":{"path":["admin","subscription"],"host":["{{baseUrl}}"],"query":[],"variable":[]},"header":[{"key":"Accept","value":"application/json"}],"method":"GET","body":{}},"status":"OK","code":200,"header":[{"key":"Content-Type","value":"application/json"}],"body":"{\n  \"created_at\": \"<string>\",\n  \"description\": \"<string>\",\n  \"duration_days\": \"<integer>\",\n  \"id\": \"<integer>\",\n  \"is_active\": \"<boolean>\",\n  \"name\": \"<string>\",\n  \"price\": \"<number>\",\n  \"updated_at\": \"<string>\"\n}","cookie":[],"_postman_previewlanguage":"json"},{"id":"cd108872-fa08-44a6-a1ff-d0b6cfdf4529","name":"Internal Server Error","originalRequest":{"url":{"path":["admin","subscription"],"host":["{{baseUrl}}"],"query":[],"variable":[]},"header":[{"key":"Accept","value":"application/json"}],"method":"GET","body":{}},"status":"Internal Server Error","code":500,"header":[{"key":"Content-Type","value":"application/json"}],"body":"{\n  \"code\": \"<integer>\",\n  \"message\": \"<string>\"\n}","cookie":[],"_postman_previewlanguage":"json"}],"event":[],"protocolProfileBehavior":{"disableBodyPruning":true}},{"id":"1f2a6ed5-b39a-4961-b700-49373200c2e2","name":"Create a new subscription","request":{"name":"Create a new subscription","description":{"content":"create a new subscription","type":"text/plain"},"url":{"path":["admin","subscription"],"host":["{{baseUrl}}"],"query":[],"variable":[]},"header":[{"key":"Accept","value":"application/json"}],"method":"POST","body":{},"auth":null},"response":[{"id":"47e78e5f-8b8f-409f-b923-ca26a12530cb","name":"OK","originalRequest":{"url":{"path":["admin","subscription"],"host":["{{baseUrl}}"],"query":[],"variable":[]},"header":[{"key":"Accept","value":"application/json"}],"method":"POST","body":{}},"status":"OK","code":200,"header":[{"key":"Content-Type","value":"application/json"}],"body":"{\n  \"created_at\": \"<string>\",\n  \"description\": \"<string>\",\n  \"duration_days\": \"<integer>\",\n  \"id\": \"<integer>\",\n  \"is_active\": \"<boolean>\",\n  \"name\": \"<string>\",\n  \"price\": \"<number>\",\n  \"updated_at\": \"<string>\"\n}","cookie":[],"_postman_previewlanguage":"json"},{"id":"6e0caa60-746f-48b7-b501-f8978ede8994","name":"Bad Request","originalRequest":{"url":{"path":["admin","subscription"],"host":["{{baseUrl}}"],"query":[],"variable":[]},"header":[{"key":"Accept","value":"application/json"}],"method":"POST","body":{}},"status":"Bad Request","code":400,"header":[{"key":"Content-Type","value":"application/json"}],"body":"{\n  \"code\": \"<integer>\",\n  \"message\": \"<string>\"\n}","cookie":[],"_postman_previewlanguage":"json"},{"id":"abf85607-10a2-4616-9257-bf87f22ee45f","name":"Internal Server Error","originalRequest":{"url":{"path":["admin","subscription"],"host":["{{baseUrl}}"],"query":[],"variable":[]},"header":[{"key":"Accept","value":"application/json"}],"method":"POST","body":{}},"status":"Internal Server Error","code":500,"header":[{"key":"Content-Type","value":"application/json"}],"body":"{\n  \"code\": \"<integer>\",\n  \"message\": \"<string>\"\n}","cookie":[],"_postman_previewlanguage":"json"}],"event":[],"protocolProfileBehavior":{"disableBodyPruning":true}},{"name":"{id}","description":"","item":[{"id":"23f5e1e4-9de1-4bef-b199-bd561ae3ef7f","name":"Get a subscription","request":{"name":"Get a subscription","description":{"content":"get a subscription","type":"text/plain"},"url":{"path":["admin","subscription",":id"],"host":["{{baseUrl}}"],"query":[],"variable":[{"type":"any","value":"<integer>","key":"id","disabled":false,"description":{"content":"(Required) Subscription ID","type":"text/plain"}}]},"header":[{"key":"Accept","value":"application/json"}],"method":"GET","body":{},"auth":null},"response":[{"id":"78ceb7ce-74a6-48e3-a223-e4247b1718da","name":"OK","originalRequest":{"url":{"path":["admin","subscription",":id"],"host":["{{baseUrl}}"],"query":[],"variable":[{"disabled":false,"description":{"content":"(Required) Subscription ID","type":"text/plain"},"type":"any","value":"<integer>","key":"id"}]},"header":[{"key":"Accept","value":"application/json"}],"method":"GET","body":{}},"status":"OK","code":200,"header":[{"key":"Content-Type","value":"application/json"}],"body":"{\n  \"created_at\": \"<string>\",\n  \"description\": \"<string>\",\n  \"duration_days\": \"<integer>\",\n  \"id\": \"<integer>\",\n  \"is_active\": \"<boolean>\",\n  \"name\": \"<string>\",\n  \"price\": \"<number>\",\n  \"updated_at\": \"<string>\"\n}","cookie":[],"_postman_previewlanguage":"json"},{"id":"f4ea396f-e853-4644-aca2-52c652ddac29","name":"Bad Request","originalRequest":{"url":{"path":["admin","subscription",":id"],"host":["{{baseUrl}}"],"query":[],"variable":[{"disabled":false,"description":{"content":"(Required) Subscription ID","type":"text/plain"},"type":"any","value":"<integer>","key":"id"}]},"header":[{"key":"Accept","value":"application/json"}],"method":"GET","body":{}},"status":"Bad Request","code":400,"header":[{"key":"Content-Type","value":"application/json"}],"body":"{\n  \"code\": \"<integer>\",\n  \"message\": \"<string>\"\n}","cookie":[],"_postman_previewlanguage":"json"},{"id":"2f6580d1-9979-4014-a21f-ec9d399faa09","name":"Internal Server Error","originalRequest":{"url":{"path":["admin","subscription",":id"],"host":["{{baseUrl}}"],"query":[],"variable":[{"disabled":false,"description":{"content":"(Required) Subscription ID","type":"text/plain"},"type":"any","value":"<integer>","key":"id"}]},"header":[{"key":"Accept","value":"application/json"}],"method":"GET","body":{}},"status":"Internal Server Error","code":500,"header":[{"key":"Content-Type","value":"application/json"}],"body":"{\n  \"code\": \"<integer>\",\n  \"message\": \"<string>\"\n}","cookie":[],"_postman_previewlanguage":"json"}],"event":[],"protocolProfileBehavior":{"disableBodyPruning":true}},{"id":"68dd2720-819c-4867-abf1-7c16395baf51","name":"Update a subscription","request":{"name":"Update a subscription","description":{"content":"update a subscription","type":"text/plain"},"url":{"path":["admin","subscription",":id"],"host":["{{baseUrl}}"],"query":[],"variable":[{"type":"any","value":"<integer>","key":"id","disabled":false,"description":{"content":"(Required) Subscription ID","type":"text/plain"}}]},"header":[{"key":"Accept","value":"application/json"}],"method":"PUT","body":{},"auth":null},"response":[{"id":"8a1bf2aa-7215-4729-8193-30518a348a35","name":"OK","originalRequest":{"url":{"path":["admin","subscription",":id"],"host":["{{baseUrl}}"],"query":[],"variable":[{"disabled":false,"description":{"content":"(Required) Subscription ID","type":"text/plain"},"type":"any","value":"<integer>","key":"id"}]},"header":[{"key":"Accept","value":"application/json"}],"method":"PUT","body":{}},"status":"OK","code":200,"header":[{"key":"Content-Type","value":"application/json"}],"body":"{\n  \"created_at\": \"<string>\",\n  \"description\": \"<string>\",\n  \"duration_days\": \"<integer>\",\n  \"id\": \"<integer>\",\n  \"is_active\": \"<boolean>\",\n  \"name\": \"<string>\",\n  \"price\": \"<number>\",\n  \"updated_at\": \"<string>\"\n}","cookie":[],"_postman_previewlanguage":"json"},{"id":"586378a0-fa8d-452f-b500-3def0df22200","name":"Bad Request","originalRequest":{"url":{"path":["admin","subscription",":id"],"host":["{{baseUrl}}"],"query":[],"variable":[{"disabled":false,"description":{"content":"(Required) Subscription ID","type":"text/plain"},"type":"any","value":"<integer>","key":"id"}]},"header":[{"key":"Accept","value":"application/json"}],"method":"PUT","body":{}},"status":"Bad Request","code":400,"header":[{"key":"Content-Type","value":"application/json"}],"body":"{\n  \"code\": \"<integer>\",\n  \"message\": \"<string>\"\n}","cookie":[],"_postman_previewlanguage":"json"},{"id":"c0ddcf1c-7154-4abc-9a66-5b97598127d2","name":"Internal Server Error","originalRequest":{"url":{"path":["admin","subscription",":id"],"host":["{{baseUrl}}"],"query":[],"variable":[{"disabled":false,"description":{"content":"(Required) Subscription ID","type":"text/plain"},"type":"any","value":"<integer>","key":"id"}]},"header":[{"key":"Accept","value":"application/json"}],"method":"PUT","body":{}},"status":"Internal Server Error","code":500,"header":[{"key":"Content-Type","value":"application/json"}],"body":"{\n  \"code\": \"<integer>\",\n  \"message\": \"<string>\"\n}","cookie":[],"_postman_previewlanguage":"json"}],"event":[],"protocolProfileBehavior":{"disableBodyPruning":true}},{"id":"74083944-6c68-4192-9247-45ef3929af3e","name":"Delete a subscription","request":{"name":"Delete a subscription","description":{"content":"delete a subscription","type":"text/plain"},"url":{"path":["admin","subscription",":id"],"host":["{{baseUrl}}"],"query":[],"variable":[{"type":"any","value":"<integer>","key":"id","disabled":false,"description":{"content":"(Required) Subscription ID","type":"text/plain"}}]},"header":[{"key":"Accept","value":"application/json"}],"method":"DELETE","body":{},"auth":null},"response":[{"id":"540d6964-66c3-4fe1-a309-413bf28dad26","name":"OK","originalRequest":{"url":{"path":["admin","subscription",":id"],"host":["{{baseUrl}}"],"query":[],"variable":[{"disabled":false,"description":{"content":"(Required) Subscription ID","type":"text/plain"},"type":"any","value":"<integer>","key":"id"}]},"header":[{"key":"Accept","value":"application/json"}],"method":"DELETE","body":{}},"status":"OK","code":200,"header":[{"key":"Content-Type","value":"application/json"}],"body":"{\n  \"key_0\": \"<string>\",\n  \"key_1\": \"<string>\"\n}","cookie":[],"_postman_previewlanguage":"json"},{"id":"205b03ce-1a00-49b8-baa3-d52148253cde","name":"Bad Request","originalRequest":{"url":{"path":["admin","subscription",":id"],"host":["{{baseUrl}}"],"query":[],"variable":[{"disabled":false,"description":{"content":"(Required) Subscription ID","type":"text/plain"},"type":"any","value":"<integer>","key":"id"}]},"header":[{"key":"Accept","value":"application/json"}],"method":"DELETE","body":{}},"status":"Bad Request","code":400,"header":[{"key":"Content-Type","value":"application/json"}],"body":"{\n  \"code\": \"<integer>\",\n  \"message\": \"<string>\"\n}","cookie":[],"_postman_previewlanguage":"json"},{"id":"a4be0f83-189f-4ddd-8792-ab4abd09f791","name":"Internal Server Error","originalRequest":{"url":{"path":["admin","subscription",":id"],"host":["{{baseUrl}}"],"query":[],"variable":[{"disabled":false,"description":{"content":"(Required) Subscription ID","type":"text/plain"},"type":"any","value":"<integer>","key":"id"}]},"header":[{"key":"Accept","value":"application/json"}],"method":"DELETE","body":{}},"status":"Internal Server Error","code":500,"header":[{"key":"Content-Type","value":"application/json"}],"body":"{\n  \"code\": \"<integer>\",\n  \"message\": \"<string>\"\n}","cookie":[],"_postman_previewlanguage":"json"}],"event":[],"protocolProfileBehavior":{"disableBodyPruning":true}}]}]}]},{"name":"auth","description":"","item":[{"name":"google","description":"","item":[{"id":"4ce1b46c-5eb6-440f-9162-cd54fab8c366","name":"Get Google OAuth consent-screen URL","request":{"name":"Get Google OAuth consent-screen URL","description":{"content":"get Google OAuth consent-screen URL","type":"text/plain"},"url":{"path":["auth","google"],"host":["{{baseUrl}}"],"query":[],"variable":[]},"header":[{"key":"Accept","value":"application/json"}],"method":"GET","body":{},"auth":null},"response":[{"id":"aab64ced-2c74-4ce1-b425-41e78191d4ab","name":"OK","originalRequest":{"url":{"path":["auth","google"],"host":["{{baseUrl}}"],"query":[],"variable":[]},"header":[{"key":"Accept","value":"application/json"}],"method":"GET","body":{}},"status":"OK","code":200,"header":[{"key":"Content-Type","value":"application/json"}],"body":"{\n  \"url\": \"<string>\"\n}","cookie":[],"_postman_previewlanguage":"json"},{"id":"be58ef3e-f946-4759-a9ba-162904ebafe5","name":"Bad Request","originalRequest":{"url":{"path":["auth","google"],"host":["{{baseUrl}}"],"query":[],"variable":[]},"header":[{"key":"Accept","value":"application/json"}],"method":"GET","body":{}},"status":"Bad Request","code":400,"header":[{"key":"Content-Type","value":"application/json"}],"body":"{\n  \"code\": \"<integer>\",\n  \"message\": \"<string>\"\n}","cookie":[],"_postman_previewlanguage":"json"},{"id":"3be6c936-c7bf-40e2-852d-4dfdbe4283bc","name":"Internal Server Error","originalRequest":{"url":{"path":["auth","google"],"host":["{{baseUrl}}"],"query":[],"variable":[]},"header":[{"key":"Accept","value":"application/json"}],"method":"GET","body":{}},"status":"Internal Server Error","code":500,"header":[{"key":"Content-Type","value":"application/json"}],"body":"{\n  \"code\": \"<integer>\",\n  \"message\": \"<string>\"\n}","cookie":[],"_postman_previewlanguage":"json"}],"event":[],"protocolProfileBehavior":{"disableBodyPruning":true}},{"name":"callback","description":"","item":[{"id":"6441db96-d0db-42ac-a7c3-b55091099307","name":"Handle Google OAuth callback","request":{"name":"Handle Google OAuth callback","description":{"content":"handle Google OAuth callback","type":"text/plain"},"url":{"path":["auth","google","callback"],"host":["{{baseUrl}}"],"query":[],"variable":[]},"header":[{"key":"Accept","value":"application/json"}],"method":"GET","body":{},"auth":null},"response":[{"id":"e2f0b947-79a2-4a56-ab14-f89c89268da0","name":"OK","originalRequest":{"url":{"path":["auth","google","callback"],"host":["{{baseUrl}}"],"query":[],"variable":[]},"header":[{"key":"Accept","value":"application/json"}],"method":"GET","body":{}},"status":"OK","code":200,"header":[{"key":"Content-Type","value":"application/json"}],"body":"{\n  \"access_token\": \"<string>\",\n  \"is_superadmin\": \"<boolean>\",\n  \"refresh_token\": \"<string>\"\n}","cookie":[],"_postman_previewlanguage":"json"},{"id":"2fe4e787-8fde-4c31-8e10-521223839865","name":"Bad Request","originalRequest":{"url":{"path":["auth","google","callback"],"host":["{{baseUrl}}"],"query":[],"variable":[]},"header":[{"key":"Accept","value":"application/json"}],"method":"GET","body":{}},"status":"Bad Request","code":400,"header":[{"key":"Content-Type","value":"application/json"}],"body":"{\n  \"code\": \"<integer>\",\n  \"message\": \"<string>\"\n}","cookie":[],"_postman_previewlanguage":"json"},{"id":"1b2b79a3-580e-4ba5-8848-7eeb63d75bfd","name":"Internal Server Error","originalRequest":{"url":{"path":["auth","google","callback"],"host":["{{baseUrl}}"],"query":[],"variable":[]},"header":[{"key":"Accept","value":"application/json"}],"method":"GET","body":{}},"status":"Internal Server Error","code":500,"header":[{"key":"Content-Type","value":"application/json"}],"body":"{\n  \"code\": \"<integer>\",\n  \"message\": \"<string>\"\n}","cookie":[],"_postman_previewlanguage":"json"}],"event":[],"protocolProfileBehavior":{"disableBodyPruning":true}}]}]},{"name":"login","description":"","item":[{"id":"e96bd287-467f-42f1-bc09-5e9205f9ec9c","name":"Login a user","request":{"name":"Login a user","description":{"content":"login a user","type":"text/plain"},"url":{"path":["auth","login"],"host":["{{baseUrl}}"],"query":[],"variable":[]},"header":[{"key":"Accept","value":"application/json"}],"method":"POST","body":{},"auth":null},"response":[{"id":"ab2150ba-7e4b-4585-a253-35c31229b223","name":"OK","originalRequest":{"url":{"path":["auth","login"],"host":["{{baseUrl}}"],"query":[],"variable":[]},"header":[{"key":"Accept","value":"application/json"}],"method":"POST","body":{}},"status":"OK","code":200,"header":[{"key":"Content-Type","value":"application/json"}],"body":"{\n  \"access_token\": \"<string>\",\n  \"is_superadmin\": \"<boolean>\",\n  \"refresh_token\": \"<string>\"\n}","cookie":[],"_postman_previewlanguage":"json"},{"id":"53c21d78-4ba0-4cfa-bba7-a757e555e579","name":"Bad Request","originalRequest":{"url":{"path":["auth","login"],"host":["{{baseUrl}}"],"query":[],"variable":[]},"header":[{"key":"Accept","value":"application/json"}],"method":"POST","body":{}},"status":"Bad Request","code":400,"header":[{"key":"Content-Type","value":"application/json"}],"body":"{\n  \"code\": \"<integer>\",\n  \"message\": \"<string>\"\n}","cookie":[],"_postman_previewlanguage":"json"},{"id":"c5e1e199-0d9d-448f-8094-b601c628689b","name":"Unauthorized","originalRequest":{"url":{"path":["auth","login"],"host":["{{baseUrl}}"],"query":[],"variable":[]},"header":[{"key":"Accept","value":"application/json"}],"method":"POST","body":{}},"status":"Unauthorized","code":401,"header":[{"key":"Content-Type","value":"application/json"}],"body":"{\n  \"code\": \"<integer>\",\n  \"message\": \"<string>\"\n}","cookie":[],"_postman_previewlanguage":"json"},{"id":"59b37adc-d5fe-4aca-86c7-5185c9a93d24","name":"Internal Server Error","originalRequest":{"url":{"path":["auth","login"],"host":["{{baseUrl}}"],"query":[],"variable":[]},"header":[{"key":"Accept","value":"application/json"}],"method":"POST","body":{}},"status":"Internal Server Error","code":500,"header":[{"key":"Content-Type","value":"application/json"}],"body":"{\n  \"code\": \"<integer>\",\n  \"message\": \"<string>\"\n}","cookie":[],"_postman_previewlanguage":"json"}],"event":[],"protocolProfileBehavior":{"disableBodyPruning":true}}]},{"name":"register","description":"","item":[{"id":"234c1a66-f0c1-498b-bf5c-df104cd2ebd1","name":"Register a new user","request":{"name":"Register a new user","description":{"content":"register a new user","type":"text/plain"},"url":{"path":["auth","register"],"host":["{{baseUrl}}"],"query":[],"variable":[]},"header":[{"key":"Accept","value":"application/json"}],"method":"POST","body":{},"auth":null},"response":[{"id":"6d53cc8f-494b-407e-b38d-ea7f4585c144","name":"OK","originalRequest":{"url":{"path":["auth","register"],"host":["{{baseUrl}}"],"query":[],"variable":[]},"header":[{"key":"Accept","value":"application/json"}],"method":"POST","body":{}},"status":"OK","code":200,"header":[{"key":"Content-Type","value":"application/json"}],"body":"{\n  \"created_at\": \"<string>\",\n  \"email\": \"<string>\",\n  \"first_name\": \"<string>\",\n  \"id\": \"<string>\",\n  \"is_superadmin\": \"<boolean>\",\n  \"last_name\": \"<string>\",\n  \"phone\": \"<string>\",\n  \"updated_at\": \"<string>\"\n}","cookie":[],"_postman_previewlanguage":"json"},{"id":"2255e603-07f6-43a0-a1c3-d0e6b5d8fe6d","name":"Bad Request","originalRequest":{"url":{"path":["auth","register"],"host":["{{baseUrl}}"],"query":[],"variable":[]},"header":[{"key":"Accept","value":"application/json"}],"method":"POST","body":{}},"status":"Bad Request","code":400,"header":[{"key":"Content-Type","value":"application/json"}],"body":"{\n  \"code\": \"<integer>\",\n  \"message\": \"<string>\"\n}","cookie":[],"_postman_previewlanguage":"json"},{"id":"6d4a62da-6fb9-41ae-afa5-315594edb780","name":"Conflict","originalRequest":{"url":{"path":["auth","register"],"host":["{{baseUrl}}"],"query":[],"variable":[]},"header":[{"key":"Accept","value":"application/json"}],"method":"POST","body":{}},"status":"Conflict","code":409,"header":[{"key":"Content-Type","value":"application/json"}],"body":"{\n  \"code\": \"<integer>\",\n  \"message\": \"<string>\"\n}","cookie":[],"_postman_previewlanguage":"json"},{"id":"afa16f33-c144-43ae-8659-fb6fc61cb767","name":"Internal Server Error","originalRequest":{"url":{"path":["auth","register"],"host":["{{baseUrl}}"],"query":[],"variable":[]},"header":[{"key":"Accept","value":"application/json"}],"method":"POST","body":{}},"status":"Internal Server Error","code":500,"header":[{"key":"Content-Type","value":"application/json"}],"body":"{\n  \"code\": \"<integer>\",\n  \"message\": \"<string>\"\n}","cookie":[],"_postman_previewlanguage":"json"}],"event":[],"protocolProfileBehavior":{"disableBodyPruning":true}}]}]},{"name":"practitioner","description":"","item":[{"id":"f580db50-0d3d-4af8-925e-16cb84411a42","name":"List practitioners","request":{"name":"List practitioners","description":{"content":"list practitioners","type":"text/plain"},"url":{"path":["practitioner"],"host":["{{baseUrl}}"],"query":[],"variable":[]},"header":[{"key":"Accept","value":"application/json"}],"method":"GET","body":{},"auth":null},"response":[{"id":"7efb9af1-b766-4338-bd9d-8762e04f5a59","name":"OK","originalRequest":{"url":{"path":["practitioner"],"host":["{{baseUrl}}"],"query":[],"variable":[]},"header":[{"key":"Accept","value":"application/json"}],"method":"GET","body":{}},"status":"OK","code":200,"header":[{"key":"Content-Type","value":"application/json"}],"body":"{\n  \"abn\": \"<string>\",\n  \"created_at\": \"<string>\",\n  \"id\": \"<string>\",\n  \"updated_at\": \"<string>\",\n  \"user_id\": \"<string>\",\n  \"verified\": \"<boolean>\"\n}","cookie":[],"_postman_previewlanguage":"json"},{"id":"5ebfa76b-4702-420e-bebf-ec31dadd8242","name":"Internal Server Error","originalRequest":{"url":{"path":["practitioner"],"host":["{{baseUrl}}"],"query":[],"variable":[]},"header":[{"key":"Accept","value":"application/json"}],"method":"GET","body":{}},"status":"Internal Server Error","code":500,"header":[{"key":"Content-Type","value":"application/json"}],"body":"{\n  \"code\": \"<integer>\",\n  \"message\": \"<string>\"\n}","cookie":[],"_postman_previewlanguage":"json"}],"event":[],"protocolProfileBehavior":{"disableBodyPruning":true}},{"id":"5d923bf8-eb58-422e-a25b-abf969050e80","name":"Create a new practitioner","request":{"name":"Create a new practitioner","description":{"content":"create a new practitioner","type":"text/plain"},"url":{"path":["practitioner"],"host":["{{baseUrl}}"],"query":[],"variable":[]},"header":[{"key":"Accept","value":"application/json"}],"method":"POST","body":{},"auth":null},"response":[{"id":"9d24c5d8-3573-4791-a520-e86c8f5425cb","name":"OK","originalRequest":{"url":{"path":["practitioner"],"host":["{{baseUrl}}"],"query":[],"variable":[]},"header":[{"key":"Accept","value":"application/json"}],"method":"POST","body":{}},"status":"OK","code":200,"header":[{"key":"Content-Type","value":"application/json"}],"body":"{\n  \"abn\": \"<string>\",\n  \"created_at\": \"<string>\",\n  \"id\": \"<string>\",\n  \"updated_at\": \"<string>\",\n  \"user_id\": \"<string>\",\n  \"verified\": \"<boolean>\"\n}","cookie":[],"_postman_previewlanguage":"json"},{"id":"52611d41-c5be-4e68-a634-8fa03f42a0c8","name":"Bad Request","originalRequest":{"url":{"path":["practitioner"],"host":["{{baseUrl}}"],"query":[],"variable":[]},"header":[{"key":"Accept","value":"application/json"}],"method":"POST","body":{}},"status":"Bad Request","code":400,"header":[{"key":"Content-Type","value":"application/json"}],"body":"{\n  \"code\": \"<integer>\",\n  \"message\": \"<string>\"\n}","cookie":[],"_postman_previewlanguage":"json"},{"id":"e4e483ad-1f06-4c0d-aacd-98d66a3be162","name":"Internal Server Error","originalRequest":{"url":{"path":["practitioner"],"host":["{{baseUrl}}"],"query":[],"variable":[]},"header":[{"key":"Accept","value":"application/json"}],"method":"POST","body":{}},"status":"Internal Server Error","code":500,"header":[{"key":"Content-Type","value":"application/json"}],"body":"{\n  \"code\": \"<integer>\",\n  \"message\": \"<string>\"\n}","cookie":[],"_postman_previewlanguage":"json"}],"event":[],"protocolProfileBehavior":{"disableBodyPruning":true}},{"name":"setting","description":"","item":[{"name":"{id}","description":"","item":[{"id":"0d15d2c5-f3ed-4558-83c6-f5ff827f1f27","name":"Get a setting by practitioner ID","request":{"name":"Get a setting by practitioner ID","description":{"content":"get a setting by practitioner ID","type":"text/plain"},"url":{"path":["practitioner","setting",":id"],"host":["{{baseUrl}}"],"query":[],"variable":[{"type":"any","value":"<string>","key":"id","disabled":false,"description":{"content":"(Required) Practitioner ID","type":"text/plain"}}]},"header":[{"key":"Accept","value":"application/json"}],"method":"GET","body":{},"auth":null},"response":[{"id":"65577869-58c4-43de-b91e-69fbb4e09685","name":"OK","originalRequest":{"url":{"path":["practitioner","setting",":id"],"host":["{{baseUrl}}"],"query":[],"variable":[{"disabled":false,"description":{"content":"(Required) Practitioner ID","type":"text/plain"},"type":"any","value":"<string>","key":"id"}]},"header":[{"key":"Accept","value":"application/json"}],"method":"GET","body":{}},"status":"OK","code":200,"header":[{"key":"Content-Type","value":"application/json"}],"body":"{\n  \"color\": \"<string>\",\n  \"created_at\": \"<string>\",\n  \"id\": \"<integer>\",\n  \"logo\": \"<string>\",\n  \"practitioner_id\": \"<string>\",\n  \"timezone\": \"<string>\",\n  \"updated_at\": \"<string>\"\n}","cookie":[],"_postman_previewlanguage":"json"},{"id":"69020961-e98c-47b2-81e6-3afbb304f94b","name":"Bad Request","originalRequest":{"url":{"path":["practitioner","setting",":id"],"host":["{{baseUrl}}"],"query":[],"variable":[{"disabled":false,"description":{"content":"(Required) Practitioner ID","type":"text/plain"},"type":"any","value":"<string>","key":"id"}]},"header":[{"key":"Accept","value":"application/json"}],"method":"GET","body":{}},"status":"Bad Request","code":400,"header":[{"key":"Content-Type","value":"application/json"}],"body":"{\n  \"code\": \"<integer>\",\n  \"message\": \"<string>\"\n}","cookie":[],"_postman_previewlanguage":"json"},{"id":"40f7a829-08ce-4acd-8085-d90e70f8bd0c","name":"Internal Server Error","originalRequest":{"url":{"path":["practitioner","setting",":id"],"host":["{{baseUrl}}"],"query":[],"variable":[{"disabled":false,"description":{"content":"(Required) Practitioner ID","type":"text/plain"},"type":"any","value":"<string>","key":"id"}]},"header":[{"key":"Accept","value":"application/json"}],"method":"GET","body":{}},"status":"Internal Server Error","code":500,"header":[{"key":"Content-Type","value":"application/json"}],"body":"{\n  \"code\": \"<integer>\",\n  \"message\": \"<string>\"\n}","cookie":[],"_postman_previewlanguage":"json"}],"event":[],"protocolProfileBehavior":{"disableBodyPruning":true}},{"id":"c7883fa0-ea8a-47e7-bff0-94e5c62182d0","name":"Upsert a setting by practitioner ID","request":{"name":"Upsert a setting by practitioner ID","description":{"content":"upsert a setting by practitioner ID","type":"text/plain"},"url":{"path":["practitioner","setting",":id"],"host":["{{baseUrl}}"],"query":[],"variable":[{"type":"any","value":"<string>","key":"id","disabled":false,"description":{"content":"(Required) Practitioner ID","type":"text/plain"}}]},"header":[{"key":"Accept","value":"application/json"}],"method":"PUT","body":{},"auth":null},"response":[{"id":"a0a90a44-9ca0-41fe-a3be-3fc0056b7de4","name":"OK","originalRequest":{"url":{"path":["practitioner","setting",":id"],"host":["{{baseUrl}}"],"query":[],"variable":[{"disabled":false,"description":{"content":"(Required) Practitioner ID","type":"text/plain"},"type":"any","value":"<string>","key":"id"}]},"header":[{"key":"Accept","value":"application/json"}],"method":"PUT","body":{}},"status":"OK","code":200,"header":[{"key":"Content-Type","value":"application/json"}],"body":"{\n  \"color\": \"<string>\",\n  \"created_at\": \"<string>\",\n  \"id\": \"<integer>\",\n  \"logo\": \"<string>\",\n  \"practitioner_id\": \"<string>\",\n  \"timezone\": \"<string>\",\n  \"updated_at\": \"<string>\"\n}","cookie":[],"_postman_previewlanguage":"json"},{"id":"95e27dd5-7edd-4bec-8078-e771b5b8a954","name":"Bad Request","originalRequest":{"url":{"path":["practitioner","setting",":id"],"host":["{{baseUrl}}"],"query":[],"variable":[{"disabled":false,"description":{"content":"(Required) Practitioner ID","type":"text/plain"},"type":"any","value":"<string>","key":"id"}]},"header":[{"key":"Accept","value":"application/json"}],"method":"PUT","body":{}},"status":"Bad Request","code":400,"header":[{"key":"Content-Type","value":"application/json"}],"body":"{\n  \"code\": \"<integer>\",\n  \"message\": \"<string>\"\n}","cookie":[],"_postman_previewlanguage":"json"},{"id":"615010d3-26bd-47ba-bf63-a16c70315cb5","name":"Internal Server Error","originalRequest":{"url":{"path":["practitioner","setting",":id"],"host":["{{baseUrl}}"],"query":[],"variable":[{"disabled":false,"description":{"content":"(Required) Practitioner ID","type":"text/plain"},"type":"any","value":"<string>","key":"id"}]},"header":[{"key":"Accept","value":"application/json"}],"method":"PUT","body":{}},"status":"Internal Server Error","code":500,"header":[{"key":"Content-Type","value":"application/json"}],"body":"{\n  \"code\": \"<integer>\",\n  \"message\": \"<string>\"\n}","cookie":[],"_postman_previewlanguage":"json"}],"event":[],"protocolProfileBehavior":{"disableBodyPruning":true}}]}]},{"name":"subscription","description":"","item":[{"id":"2cffb3de-55b1-4ec9-abf5-1b5b8d313434","name":"List subscriptions by practitioner ID","request":{"name":"List subscriptions by practitioner ID","description":{"content":"list subscriptions by practitioner ID","type":"text/plain"},"url":{"path":["practitioner","subscription"],"host":["{{baseUrl}}"],"query":[],"variable":[{"disabled":false,"description":{"content":"(Required) Practitioner ID","type":"text/plain"},"type":"any","value":"<string>","key":"practitioner_id"}]},"header":[{"key":"Accept","value":"application/json"}],"method":"GET","body":{},"auth":null},"response":[{"id":"b0ebc6b3-0704-4243-9a60-c734e22b93df","name":"OK","originalRequest":{"url":{"path":["practitioner","subscription"],"host":["{{baseUrl}}"],"query":[],"variable":[{"disabled":false,"description":{"content":"(Required) Practitioner ID","type":"text/plain"},"type":"any","value":"<string>","key":"practitioner_id"}]},"header":[{"key":"Accept","value":"application/json"}],"method":"GET","body":{}},"status":"OK","code":200,"header":[{"key":"Content-Type","value":"application/json"}],"body":"{\n  \"created_at\": \"<string>\",\n  \"description\": \"<string>\",\n  \"duration_days\": \"<integer>\",\n  \"id\": \"<integer>\",\n  \"is_active\": \"<boolean>\",\n  \"name\": \"<string>\",\n  \"price\": \"<number>\",\n  \"updated_at\": \"<string>\"\n}","cookie":[],"_postman_previewlanguage":"json"},{"id":"eb0e2c9d-874c-486a-887f-7a743fadd0e1","name":"Bad Request","originalRequest":{"url":{"path":["practitioner","subscription"],"host":["{{baseUrl}}"],"query":[],"variable":[{"disabled":false,"description":{"content":"(Required) Practitioner ID","type":"text/plain"},"type":"any","value":"<string>","key":"practitioner_id"}]},"header":[{"key":"Accept","value":"application/json"}],"method":"GET","body":{}},"status":"Bad Request","code":400,"header":[{"key":"Content-Type","value":"application/json"}],"body":"{\n  \"code\": \"<integer>\",\n  \"message\": \"<string>\"\n}","cookie":[],"_postman_previewlanguage":"json"},{"id":"9adf986b-a154-49ca-afd4-3096db14ce36","name":"Internal Server Error","originalRequest":{"url":{"path":["practitioner","subscription"],"host":["{{baseUrl}}"],"query":[],"variable":[{"disabled":false,"description":{"content":"(Required) Practitioner ID","type":"text/plain"},"type":"any","value":"<string>","key":"practitioner_id"}]},"header":[{"key":"Accept","value":"application/json"}],"method":"GET","body":{}},"status":"Internal Server Error","code":500,"header":[{"key":"Content-Type","value":"application/json"}],"body":"{\n  \"code\": \"<integer>\",\n  \"message\": \"<string>\"\n}","cookie":[],"_postman_previewlanguage":"json"}],"event":[],"protocolProfileBehavior":{"disableBodyPruning":true}},{"name":"{id}","description":"","item":[{"id":"b6f7fe48-6f4e-4bbd-bf94-21e9fd709e48","name":"Get a subscription by ID","request":{"name":"Get a subscription by ID","description":{"content":"get a subscription by ID","type":"text/plain"},"url":{"path":["practitioner","subscription",":id"],"host":["{{baseUrl}}"],"query":[],"variable":[{"type":"any","value":"<integer>","key":"id","disabled":false,"description":{"content":"(Required) Subscription ID","type":"text/plain"}}]},"header":[{"key":"Accept","value":"application/json"}],"method":"GET","body":{},"auth":null},"response":[{"id":"4206141d-eef8-4cf1-a783-34c1a38c39fc","name":"OK","originalRequest":{"url":{"path":["practitioner","subscription",":id"],"host":["{{baseUrl}}"],"query":[],"variable":[{"disabled":false,"description":{"content":"(Required) Subscription ID","type":"text/plain"},"type":"any","value":"<integer>","key":"id"}]},"header":[{"key":"Accept","value":"application/json"}],"method":"GET","body":{}},"status":"OK","code":200,"header":[{"key":"Content-Type","value":"application/json"}],"body":"{\n  \"created_at\": \"<string>\",\n  \"description\": \"<string>\",\n  \"duration_days\": \"<integer>\",\n  \"id\": \"<integer>\",\n  \"is_active\": \"<boolean>\",\n  \"name\": \"<string>\",\n  \"price\": \"<number>\",\n  \"updated_at\": \"<string>\"\n}","cookie":[],"_postman_previewlanguage":"json"},{"id":"98817bdd-109c-4073-962f-8fe7f5bb8696","name":"Bad Request","originalRequest":{"url":{"path":["practitioner","subscription",":id"],"host":["{{baseUrl}}"],"query":[],"variable":[{"disabled":false,"description":{"content":"(Required) Subscription ID","type":"text/plain"},"type":"any","value":"<integer>","key":"id"}]},"header":[{"key":"Accept","value":"application/json"}],"method":"GET","body":{}},"status":"Bad Request","code":400,"header":[{"key":"Content-Type","value":"application/json"}],"body":"{\n  \"code\": \"<integer>\",\n  \"message\": \"<string>\"\n}","cookie":[],"_postman_previewlanguage":"json"},{"id":"e7d1c6b1-645a-49ae-a01b-0bfc7240ffa9","name":"Internal Server Error","originalRequest":{"url":{"path":["practitioner","subscription",":id"],"host":["{{baseUrl}}"],"query":[],"variable":[{"disabled":false,"description":{"content":"(Required) Subscription ID","type":"text/plain"},"type":"any","value":"<integer>","key":"id"}]},"header":[{"key":"Accept","value":"application/json"}],"method":"GET","body":{}},"status":"Internal Server Error","code":500,"header":[{"key":"Content-Type","value":"application/json"}],"body":"{\n  \"code\": \"<integer>\",\n  \"message\": \"<string>\"\n}","cookie":[],"_postman_previewlanguage":"json"}],"event":[],"protocolProfileBehavior":{"disableBodyPruning":true}},{"id":"15dc6b05-dcfa-4a92-9458-481f87d1e7ae","name":"Update a subscription","request":{"name":"Update a subscription","description":{"content":"update a subscription","type":"text/plain"},"url":{"path":["practitioner","subscription",":id"],"host":["{{baseUrl}}"],"query":[],"variable":[{"type":"any","value":"<integer>","key":"id","disabled":false,"description":{"content":"(Required) Subscription ID","type":"text/plain"}},{"disabled":false,"description":{"content":"(Required) Practitioner ID","type":"text/plain"},"type":"any","value":"<string>","key":"practitioner_id"}]},"header":[{"key":"Accept","value":"application/json"}],"method":"PUT","body":{},"auth":null},"response":[{"id":"1582ecd9-a280-47db-85c9-3959040b772c","name":"OK","originalRequest":{"url":{"path":["practitioner","subscription",":id"],"host":["{{baseUrl}}"],"query":[],"variable":[{"disabled":false,"description":{"content":"(Required) Subscription ID","type":"text/plain"},"type":"any","value":"<integer>","key":"id"},{"disabled":false,"description":{"content":"(Required) Practitioner ID","type":"text/plain"},"type":"any","value":"<string>","key":"practitioner_id"}]},"header":[{"key":"Accept","value":"application/json"}],"method":"PUT","body":{}},"status":"OK","code":200,"header":[{"key":"Content-Type","value":"application/json"}],"body":"{\n  \"created_at\": \"<string>\",\n  \"description\": \"<string>\",\n  \"duration_days\": \"<integer>\",\n  \"id\": \"<integer>\",\n  \"is_active\": \"<boolean>\",\n  \"name\": \"<string>\",\n  \"price\": \"<number>\",\n  \"updated_at\": \"<string>\"\n}","cookie":[],"_postman_previewlanguage":"json"},{"id":"4fc065e9-ddef-4159-ac51-cf681544ab45","name":"Bad Request","originalRequest":{"url":{"path":["practitioner","subscription",":id"],"host":["{{baseUrl}}"],"query":[],"variable":[{"disabled":false,"description":{"content":"(Required) Subscription ID","type":"text/plain"},"type":"any","value":"<integer>","key":"id"},{"disabled":false,"description":{"content":"(Required) Practitioner ID","type":"text/plain"},"type":"any","value":"<string>","key":"practitioner_id"}]},"header":[{"key":"Accept","value":"application/json"}],"method":"PUT","body":{}},"status":"Bad Request","code":400,"header":[{"key":"Content-Type","value":"application/json"}],"body":"{\n  \"code\": \"<integer>\",\n  \"message\": \"<string>\"\n}","cookie":[],"_postman_previewlanguage":"json"},{"id":"b58cdaa8-c665-4879-994e-6bebfc6b218e","name":"Internal Server Error","originalRequest":{"url":{"path":["practitioner","subscription",":id"],"host":["{{baseUrl}}"],"query":[],"variable":[{"disabled":false,"description":{"content":"(Required) Subscription ID","type":"text/plain"},"type":"any","value":"<integer>","key":"id"},{"disabled":false,"description":{"content":"(Required) Practitioner ID","type":"text/plain"},"type":"any","value":"<string>","key":"practitioner_id"}]},"header":[{"key":"Accept","value":"application/json"}],"method":"PUT","body":{}},"status":"Internal Server Error","code":500,"header":[{"key":"Content-Type","value":"application/json"}],"body":"{\n  \"code\": \"<integer>\",\n  \"message\": \"<string>\"\n}","cookie":[],"_postman_previewlanguage":"json"}],"event":[],"protocolProfileBehavior":{"disableBodyPruning":true}},{"id":"67186a9f-8e49-41e3-84b4-e547e471cdc1","name":"Delete a subscription","request":{"name":"Delete a subscription","description":{"content":"delete a subscription","type":"text/plain"},"url":{"path":["practitioner","subscription",":id"],"host":["{{baseUrl}}"],"query":[],"variable":[{"type":"any","value":"<integer>","key":"id","disabled":false,"description":{"content":"(Required) Subscription ID","type":"text/plain"}},{"disabled":false,"description":{"content":"(Required) Practitioner ID","type":"text/plain"},"type":"any","value":"<string>","key":"practitioner_id"}]},"header":[{"key":"Accept","value":"application/json"}],"method":"DELETE","body":{},"auth":null},"response":[{"id":"81f24c3a-1b98-4b42-a0aa-5502e5647322","name":"OK","originalRequest":{"url":{"path":["practitioner","subscription",":id"],"host":["{{baseUrl}}"],"query":[],"variable":[{"disabled":false,"description":{"content":"(Required) Subscription ID","type":"text/plain"},"type":"any","value":"<integer>","key":"id"},{"disabled":false,"description":{"content":"(Required) Practitioner ID","type":"text/plain"},"type":"any","value":"<string>","key":"practitioner_id"}]},"header":[{"key":"Accept","value":"application/json"}],"method":"DELETE","body":{}},"status":"OK","code":200,"header":[{"key":"Content-Type","value":"application/json"}],"body":"{\n  \"key_0\": \"<string>\",\n  \"key_1\": \"<string>\"\n}","cookie":[],"_postman_previewlanguage":"json"},{"id":"0983bc7d-85f8-40aa-b65f-f0c35f580646","name":"Bad Request","originalRequest":{"url":{"path":["practitioner","subscription",":id"],"host":["{{baseUrl}}"],"query":[],"variable":[{"disabled":false,"description":{"content":"(Required) Subscription ID","type":"text/plain"},"type":"any","value":"<integer>","key":"id"},{"disabled":false,"description":{"content":"(Required) Practitioner ID","type":"text/plain"},"type":"any","value":"<string>","key":"practitioner_id"}]},"header":[{"key":"Accept","value":"application/json"}],"method":"DELETE","body":{}},"status":"Bad Request","code":400,"header":[{"key":"Content-Type","value":"application/json"}],"body":"{\n  \"code\": \"<integer>\",\n  \"message\": \"<string>\"\n}","cookie":[],"_postman_previewlanguage":"json"},{"id":"9c64a0f2-1b70-4a20-8cba-d21404f263e6","name":"Internal Server Error","originalRequest":{"url":{"path":["practitioner","subscription",":id"],"host":["{{baseUrl}}"],"query":[],"variable":[{"disabled":false,"description":{"content":"(Required) Subscription ID","type":"text/plain"},"type":"any","value":"<integer>","key":"id"},{"disabled":false,"description":{"content":"(Required) Practitioner ID","type":"text/plain"},"type":"any","value":"<string>","key":"practitioner_id"}]},"header":[{"key":"Accept","value":"application/json"}],"method":"DELETE","body":{}},"status":"Internal Server Error","code":500,"header":[{"key":"Content-Type","value":"application/json"}],"body":"{\n  \"code\": \"<integer>\",\n  \"message\": \"<string>\"\n}","cookie":[],"_postman_previewlanguage":"json"}],"event":[],"protocolProfileBehavior":{"disableBodyPruning":true}}]}]},{"name":"user","description":"","item":[{"name":"{user_id}","description":"","item":[{"id":"55d0734b-7445-49c1-9166-4e3b885ad79a","name":"Get a practitioner by user ID","request":{"name":"Get a practitioner by user ID","description":{"content":"get a practitioner by user ID","type":"text/plain"},"url":{"path":["practitioner","user",":user_id"],"host":["{{baseUrl}}"],"query":[],"variable":[{"type":"any","value":"<string>","key":"user_id","disabled":false,"description":{"content":"(Required) User ID","type":"text/plain"}}]},"header":[{"key":"Accept","value":"application/json"}],"method":"GET","body":{},"auth":null},"response":[{"id":"0ff2b22a-2f27-46b7-ba24-19a72e849dac","name":"OK","originalRequest":{"url":{"path":["practitioner","user",":user_id"],"host":["{{baseUrl}}"],"query":[],"variable":[{"disabled":false,"description":{"content":"(Required) User ID","type":"text/plain"},"type":"any","value":"<string>","key":"user_id"}]},"header":[{"key":"Accept","value":"application/json"}],"method":"GET","body":{}},"status":"OK","code":200,"header":[{"key":"Content-Type","value":"application/json"}],"body":"{\n  \"abn\": \"<string>\",\n  \"created_at\": \"<string>\",\n  \"id\": \"<string>\",\n  \"updated_at\": \"<string>\",\n  \"user_id\": \"<string>\",\n  \"verified\": \"<boolean>\"\n}","cookie":[],"_postman_previewlanguage":"json"},{"id":"efbc18e4-3cb7-4b01-bf6c-c47a75413fd7","name":"Bad Request","originalRequest":{"url":{"path":["practitioner","user",":user_id"],"host":["{{baseUrl}}"],"query":[],"variable":[{"disabled":false,"description":{"content":"(Required) User ID","type":"text/plain"},"type":"any","value":"<string>","key":"user_id"}]},"header":[{"key":"Accept","value":"application/json"}],"method":"GET","body":{}},"status":"Bad Request","code":400,"header":[{"key":"Content-Type","value":"application/json"}],"body":"{\n  \"code\": \"<integer>\",\n  \"message\": \"<string>\"\n}","cookie":[],"_postman_previewlanguage":"json"},{"id":"b0bf6190-6bb0-41a5-bfc3-547323063d72","name":"Internal Server Error","originalRequest":{"url":{"path":["practitioner","user",":user_id"],"host":["{{baseUrl}}"],"query":[],"variable":[{"disabled":false,"description":{"content":"(Required) User ID","type":"text/plain"},"type":"any","value":"<string>","key":"user_id"}]},"header":[{"key":"Accept","value":"application/json"}],"method":"GET","body":{}},"status":"Internal Server Error","code":500,"header":[{"key":"Content-Type","value":"application/json"}],"body":"{\n  \"code\": \"<integer>\",\n  \"message\": \"<string>\"\n}","cookie":[],"_postman_previewlanguage":"json"}],"event":[],"protocolProfileBehavior":{"disableBodyPruning":true}}]}]},{"name":"{id}","description":"","item":[{"id":"7dab3710-23e0-43f9-b7f6-28093f544014","name":"Get a practitioner by ID","request":{"name":"Get a practitioner by ID","description":{"content":"get a practitioner by ID","type":"text/plain"},"url":{"path":["practitioner",":id"],"host":["{{baseUrl}}"],"query":[],"variable":[{"type":"any","value":"<string>","key":"id","disabled":false,"description":{"content":"(Required) Practitioner ID","type":"text/plain"}}]},"header":[{"key":"Accept","value":"application/json"}],"method":"GET","body":{},"auth":null},"response":[{"id":"fd5de2e2-ae74-4294-baf5-d8f4d4b3ac5a","name":"OK","originalRequest":{"url":{"path":["practitioner",":id"],"host":["{{baseUrl}}"],"query":[],"variable":[{"disabled":false,"description":{"content":"(Required) Practitioner ID","type":"text/plain"},"type":"any","value":"<string>","key":"id"}]},"header":[{"key":"Accept","value":"application/json"}],"method":"GET","body":{}},"status":"OK","code":200,"header":[{"key":"Content-Type","value":"application/json"}],"body":"{\n  \"abn\": \"<string>\",\n  \"created_at\": \"<string>\",\n  \"id\": \"<string>\",\n  \"updated_at\": \"<string>\",\n  \"user_id\": \"<string>\",\n  \"verified\": \"<boolean>\"\n}","cookie":[],"_postman_previewlanguage":"json"},{"id":"9dd6c209-138e-481b-bceb-6236ca25e39a","name":"Bad Request","originalRequest":{"url":{"path":["practitioner",":id"],"host":["{{baseUrl}}"],"query":[],"variable":[{"disabled":false,"description":{"content":"(Required) Practitioner ID","type":"text/plain"},"type":"any","value":"<string>","key":"id"}]},"header":[{"key":"Accept","value":"application/json"}],"method":"GET","body":{}},"status":"Bad Request","code":400,"header":[{"key":"Content-Type","value":"application/json"}],"body":"{\n  \"code\": \"<integer>\",\n  \"message\": \"<string>\"\n}","cookie":[],"_postman_previewlanguage":"json"},{"id":"48ac734c-8ccd-4a0d-8c88-f0a9337f12d8","name":"Internal Server Error","originalRequest":{"url":{"path":["practitioner",":id"],"host":["{{baseUrl}}"],"query":[],"variable":[{"disabled":false,"description":{"content":"(Required) Practitioner ID","type":"text/plain"},"type":"any","value":"<string>","key":"id"}]},"header":[{"key":"Accept","value":"application/json"}],"method":"GET","body":{}},"status":"Internal Server Error","code":500,"header":[{"key":"Content-Type","value":"application/json"}],"body":"{\n  \"code\": \"<integer>\",\n  \"message\": \"<string>\"\n}","cookie":[],"_postman_previewlanguage":"json"}],"event":[],"protocolProfileBehavior":{"disableBodyPruning":true}},{"id":"0a149fc9-34c3-4f4b-a258-56f71ceaf50c","name":"Update a practitioner","request":{"name":"Update a practitioner","description":{"content":"update a practitioner","type":"text/plain"},"url":{"path":["practitioner",":id"],"host":["{{baseUrl}}"],"query":[],"variable":[{"type":"any","value":"<string>","key":"id","disabled":false,"description":{"content":"(Required) Practitioner ID","type":"text/plain"}}]},"header":[{"key":"Accept","value":"application/json"}],"method":"PUT","body":{},"auth":null},"response":[{"id":"8dd61d58-c106-4ead-bb54-d705d2d9b9ae","name":"OK","originalRequest":{"url":{"path":["practitioner",":id"],"host":["{{baseUrl}}"],"query":[],"variable":[{"disabled":false,"description":{"content":"(Required) Practitioner ID","type":"text/plain"},"type":"any","value":"<string>","key":"id"}]},"header":[{"key":"Accept","value":"application/json"}],"method":"PUT","body":{}},"status":"OK","code":200,"header":[{"key":"Content-Type","value":"application/json"}],"body":"{\n  \"abn\": \"<string>\",\n  \"created_at\": \"<string>\",\n  \"id\": \"<string>\",\n  \"updated_at\": \"<string>\",\n  \"user_id\": \"<string>\",\n  \"verified\": \"<boolean>\"\n}","cookie":[],"_postman_previewlanguage":"json"},{"id":"620c13de-6dce-477e-8d8b-9cbb1a580c37","name":"Bad Request","originalRequest":{"url":{"path":["practitioner",":id"],"host":["{{baseUrl}}"],"query":[],"variable":[{"disabled":false,"description":{"content":"(Required) Practitioner ID","type":"text/plain"},"type":"any","value":"<string>","key":"id"}]},"header":[{"key":"Accept","value":"application/json"}],"method":"PUT","body":{}},"status":"Bad Request","code":400,"header":[{"key":"Content-Type","value":"application/json"}],"body":"{\n  \"code\": \"<integer>\",\n  \"message\": \"<string>\"\n}","cookie":[],"_postman_previewlanguage":"json"},{"id":"2a4239cb-5a34-44be-bbb9-6ce9bbc628cd","name":"Internal Server Error","originalRequest":{"url":{"path":["practitioner",":id"],"host":["{{baseUrl}}"],"query":[],"variable":[{"disabled":false,"description":{"content":"(Required) Practitioner ID","type":"text/plain"},"type":"any","value":"<string>","key":"id"}]},"header":[{"key":"Accept","value":"application/json"}],"method":"PUT","body":{}},"status":"Internal Server Error","code":500,"header":[{"key":"Content-Type","value":"application/json"}],"body":"{\n  \"code\": \"<integer>\",\n  \"message\": \"<string>\"\n}","cookie":[],"_postman_previewlanguage":"json"}],"event":[],"protocolProfileBehavior":{"disableBodyPruning":true}},{"id":"91e9b805-e60b-448d-93ec-57a44932b380","name":"Delete a practitioner","request":{"name":"Delete a practitioner","description":{"content":"delete a practitioner","type":"text/plain"},"url":{"path":["practitioner",":id"],"host":["{{baseUrl}}"],"query":[],"variable":[{"type":"any","value":"<string>","key":"id","disabled":false,"description":{"content":"(Required) Practitioner ID","type":"text/plain"}}]},"header":[{"key":"Accept","value":"application/json"}],"method":"DELETE","body":{},"auth":null},"response":[{"id":"e04c5b3b-69e4-491b-9960-5ee5ef34768e","name":"OK","originalRequest":{"url":{"path":["practitioner",":id"],"host":["{{baseUrl}}"],"query":[],"variable":[{"disabled":false,"description":{"content":"(Required) Practitioner ID","type":"text/plain"},"type":"any","value":"<string>","key":"id"}]},"header":[{"key":"Accept","value":"application/json"}],"method":"DELETE","body":{}},"status":"OK","code":200,"header":[{"key":"Content-Type","value":"application/json"}],"body":"{\n  \"key_0\": \"<string>\",\n  \"key_1\": \"<string>\"\n}","cookie":[],"_postman_previewlanguage":"json"},{"id":"5aa56958-bfae-4e7a-8a60-859831d8ddb9","name":"Bad Request","originalRequest":{"url":{"path":["practitioner",":id"],"host":["{{baseUrl}}"],"query":[],"variable":[{"disabled":false,"description":{"content":"(Required) Practitioner ID","type":"text/plain"},"type":"any","value":"<string>","key":"id"}]},"header":[{"key":"Accept","value":"application/json"}],"method":"DELETE","body":{}},"status":"Bad Request","code":400,"header":[{"key":"Content-Type","value":"application/json"}],"body":"{\n  \"code\": \"<integer>\",\n  \"message\": \"<string>\"\n}","cookie":[],"_postman_previewlanguage":"json"},{"id":"7f15e762-ff26-402d-888c-a892895f2b7d","name":"Internal Server Error","originalRequest":{"url":{"path":["practitioner",":id"],"host":["{{baseUrl}}"],"query":[],"variable":[{"disabled":false,"description":{"content":"(Required) Practitioner ID","type":"text/plain"},"type":"any","value":"<string>","key":"id"}]},"header":[{"key":"Accept","value":"application/json"}],"method":"DELETE","body":{}},"status":"Internal Server Error","code":500,"header":[{"key":"Content-Type","value":"application/json"}],"body":"{\n  \"code\": \"<integer>\",\n  \"message\": \"<string>\"\n}","cookie":[],"_postman_previewlanguage":"json"}],"event":[],"protocolProfileBehavior":{"disableBodyPruning":true}}]}]}],"event":[],"variable":[{"key":"baseUrl","value":"http://localhost:8080/api/v1"}],"info":{"_postman_id":"91d812f0-f78e-485b-95ee-5db4e93b9171","name":"Backend API","schema":"https://schema.getpostman.com/json/collection/v2.1.0/collection.json","description":{"content":"Backend API for acareca\n\nContact Support:\n Name: API Support","type":"text/plain"}}}